{
  "id": "16082560",
  "url": "https://news.sanook.com/lotto/check/16082560/",
  "date": "16 August 2560",
  "prize": {
    "prize_1": "715431",
    "prize_2": [
      "050755",
      "160502",
      "333699",
      "780589",
      "831514"
    ],
    "prize_3": [
      "052996",
      "225617",
      "250641",
      "405059",
      "449343",
      "536750",
      "595146",
      "692474",
      "726484",
      "730077"
    ],
    "prize_4": [
      "004485",
      "150289",
      "212628",
      "283410",
      "390517",
      "599179",
      "706379",
      "787856",
      "806567",
      "872000",
      "022824",
      "156238",
      "221340",
      "300187",
      "432642",
      "600815",
      "729865",
      "800093",
      "817787",
      "916450",
      "055909",
      "171206",
      "230363",
      "341919",
      "453205",
      "608804",
      "738435",
      "803794",
      "832863",
      "932568",
      "077788",
      "175538",
      "239136",
      "344030",
      "543939",
      "666395",
      "773262",
      "804463",
      "834982",
      "940765",
      "134941",
      "185177",
      "266094",
      "351288",
      "574494",
      "701423",
      "779529",
      "805108",
      "865922",
      "998017"
    ],
    "prize_5": [
      "005199",
      "153681",
      "252637",
      "357422",
      "405647",
      "492291",
      "566943",
      "634070",
      "787316",
      "873826",
      "027485",
      "162776",
      "264422",
      "365052",
      "410869",
      "499170",
      "585959",
      "636534",
      "792228",
      "884166",
      "031706",
      "215481",
      "276589",
      "365344",
      "414351",
      "507588",
      "586501",
      "660122",
      "803617",
      "884504",
      "041922",
      "216619",
      "283333",
      "373700",
      "415073",
      "508266",
      "590351",
      "691014",
      "803618",
      "905625",
      "047402",
      "219113",
      "289988",
      "380484",
      "416008",
      "509465",
      "594712",
      "709020",
      "806724",
      "909725",
      "050640",
      "226572",
      "306448",
      "386971",
      "420039",
      "524382",
      "595570",
      "711941",
      "823160",
      "935058",
      "074261",
      "227804",
      "329587",
      "394092",
      "428697",
      "537852",
      "597312",
      "714663",
      "833795",
      "937441",
      "077895",
      "229390",
      "332900",
      "395287",
      "429215",
      "553298",
      "616334",
      "743270",
      "834830",
      "947786",
      "084107",
      "232305",
      "353080",
      "399093",
      "443902",
      "561896",
      "618547",
      "766356",
      "839419",
      "956462",
      "088088",
      "249779",
      "355276",
      "404049",
      "474669",
      "563600",
      "622539",
      "767254",
      "860626",
      "966447"
    ],
    "prize1_close": [
      "715430",
      "715432"
    ],
    "prize_last2": "37",
    "prize_last3": [
      "253",
      "945"
    ],
    "prize_first3": [
      "115",
      "302"
    ]
  },
  "wording": {
    "prize_1": {
      "message": "ที่ 1",
      "prize": "3,000,000"
    },
    "prize_2": {
      "message": "ที่ 2",
      "prize": "100,000"
    },
    "prize1_close": {
      "message": "ข้างเคียงรางวัลที่ 1",
      "prize": "50,000"
    },
    "prize_3": {
      "message": "ที่ 3",
      "prize": "40,000"
    },
    "prize_4": {
      "message": "ที่ 4",
      "prize": "20,000"
    },
    "prize_5": {
      "message": "ที่ 5",
      "prize": "10,000"
    },
    "prize_first3": {
      "message": "เลขหน้า 3 ตัว",
      "prize": "2,000"
    },
    "prize_last3": {
      "message": "เลขท้าย 3 ตัว",
      "prize": "2,000"
    },
    "prize_last2": {
      "message": "เลขท้าย 2 ตัว",
      "prize": "1,000"
    }
  }
}