{
  "id": "16122563",
  "url": "https://news.sanook.com/lotto/check/16122563/",
  "date": "16 December 2563",
  "prize": {
    "prize_1": "201303",
    "prize_2": [
      "284694",
      "408019",
      "572443",
      "780453",
      "975617"
    ],
    "prize_3": [
      "000973",
      "011404",
      "046396",
      "332227",
      "351056",
      "358429",
      "384705",
      "387722",
      "776045",
      "859519"
    ],
    "prize_4": [
      "004474",
      "049286",
      "142804",
      "265147",
      "403954",
      "539471",
      "618838",
      "718028",
      "771583",
      "870829",
      "013055",
      "067205",
      "156987",
      "328013",
      "440322",
      "546650",
      "633683",
      "725943",
      "790366",
      "931292",
      "027611",
      "070851",
      "191570",
      "340661",
      "477967",
      "558661",
      "647375",
      "733028",
      "823257",
      "959196",
      "033205",
      "101222",
      "237943",
      "361583",
      "482652",
      "571740",
      "662143",
      "735797",
      "841863",
      "974001",
      "047151",
      "136527",
      "246487",
      "395749",
      "519802",
      "596158",
      "683116",
      "762897",
      "866456",
      "981143"
    ],
    "prize_5": [
      "006560",
      "094080",
      "209027",
      "244340",
      "317306",
      "393418",
      "570852",
      "653747",
      "733729",
      "908694",
      "016570",
      "101039",
      "209438",
      "255930",
      "332602",
      "402271",
      "573035",
      "660401",
      "738830",
      "916645",
      "018087",
      "125637",
      "218144",
      "263873",
      "345297",
      "420635",
      "575639",
      "664863",
      "758704",
      "930917",
      "028476",
      "130126",
      "218471",
      "271856",
      "367680",
      "433600",
      "575903",
      "701002",
      "789126",
      "932094",
      "030198",
      "143101",
      "221884",
      "288754",
      "368977",
      "465422",
      "581470",
      "706913",
      "839758",
      "937906",
      "036219",
      "153955",
      "224678",
      "290464",
      "376643",
      "490074",
      "602100",
      "708698",
      "859929",
      "940877",
      "038298",
      "163501",
      "224887",
      "293966",
      "377807",
      "493565",
      "608023",
      "711796",
      "863234",
      "951747",
      "046685",
      "173547",
      "226157",
      "294066",
      "378691",
      "493704",
      "612078",
      "713548",
      "879739",
      "954975",
      "057606",
      "195362",
      "236137",
      "302349",
      "379671",
      "525175",
      "617622",
      "719104",
      "894057",
      "987179",
      "085504",
      "203119",
      "236969",
      "304762",
      "386364",
      "529987",
      "623571",
      "727119",
      "897003",
      "995484"
    ],
    "prize1_close": [
      "201302",
      "201304"
    ],
    "prize_last2": "70",
    "prize_last3": [
      "072",
      "517"
    ],
    "prize_first3": [
      "377",
      "828"
    ]
  },
  "wording": {
    "prize_1": {
      "message": "ที่ 1",
      "prize": "6,000,000"
    },
    "prize_2": {
      "message": "ที่ 2",
      "prize": "200,000"
    },
    "prize1_close": {
      "message": "ข้างเคียงรางวัลที่ 1",
      "prize": "100,000"
    },
    "prize_3": {
      "message": "ที่ 3",
      "prize": "80,000"
    },
    "prize_4": {
      "message": "ที่ 4",
      "prize": "40,000"
    },
    "prize_5": {
      "message": "ที่ 5",
      "prize": "20,000"
    },
    "prize_first3": {
      "message": "เลขหน้า 3 ตัว",
      "prize": "4,000"
    },
    "prize_last3": {
      "message": "เลขท้าย 3 ตัว",
      "prize": "4,000"
    },
    "prize_last2": {
      "message": "เลขท้าย 2 ตัว",
      "prize": "2,000"
    }
  }
}